dill_tils/__init__.py
dill_tils/email/__init__.py
dill_tils/email/email.py
dill_tils/flask/__init__.py
dill_tils/flask/recaptcha.py
dill_tils/text/__init__.py
dill_tils/text/clear.py
dill_tils/text/write.py
dill_tils-1.0.8.dist-info/LICENSE
dill_tils-1.0.8.dist-info/METADATA
dill_tils-1.0.8.dist-info/WHEEL
dill_tils-1.0.8.dist-info/top_level.txt
dill_tils-1.0.8.dist-info/RECORD
