Metadata-Version: 2.1
Name: dill-tils
Version: 1.0.8
Summary: A collection of DillonB07s utilities
Home-page: https://github.com/DillonB07/dill_tils
Author: Dillon Barnes
Author-email: dillonbarnes07@gmail.com
Project-URL: Documentation, https://dill-tils.readthedocs.io/en/latest/
Project-URL: Source Code, https://github.com/DillonB07/dill_tils
Project-URL: Bug Tracker, https://github.com/DillonB07/dill_tils/issues
Project-URL: Discussions, https://github.com/DillonB07/dill_tils/discussions
Keywords: dillonb07,utils
Classifier: Programming Language :: Python :: 3
Classifier: License :: OSI Approved :: GNU Lesser General Public License v3 (LGPLv3)
Classifier: Operating System :: OS Independent
Classifier: Topic :: Utilities
Requires-Python: >=3.6
License-File: LICENSE
